setup.py
deeppostal/__init__.py
deeppostal/deeppostal.py
deeppostal.egg-info/PKG-INFO
deeppostal.egg-info/SOURCES.txt
deeppostal.egg-info/dependency_links.txt
deeppostal.egg-info/top_level.txt