Metadata-Version: 2.1
Name: deeppostal
Version: 0.0.0
Summary: A deep learning postal address parser
Author: igospatial
Classifier: Programming Language :: Python :: 3
Classifier: License :: OSI Approved :: MIT License
Classifier: Operating System :: OS Independent
Requires-Python: >=3.11
